ttrace/__init__.py
ttrace/cli.py
ttrace/core.py
ttrace/utils/__init__.py
ttrace/utils/treestuff.py
ttrace-0.1.13.dist-info/METADATA
ttrace-0.1.13.dist-info/WHEEL
ttrace-0.1.13.dist-info/entry_points.txt
ttrace-0.1.13.dist-info/RECORD
