Metadata-Version: 2.1
Name: ttrace
Version: 0.1.13
Summary: Makes use of strace
Home-page: https://projects.om-office.de/frans/ttrace.git
Author: Frans Fürst
Author-email: frans.fuerst+gitlab@protonmail.com
Requires-Python: >=3.10,<4.0
Classifier: Programming Language :: Python :: 3
Classifier: Programming Language :: Python :: 3.10
Classifier: Programming Language :: Python :: 3.11
Classifier: Programming Language :: Python :: 3.12
Requires-Dist: aiofiles (>=23,<24)
Requires-Dist: treelib (>=1.6.1,<2.0.0)
Project-URL: Repository, https://projects.om-office.de/frans/ttrace.git
